README.rst
setup.py
yamltypes/__init__.py
yamltypes/cli.py
yamltypes/yaml.py
yamltypes/yaml2rst.py
yamltypes/yamltypes.py
yamltypes.egg-info/PKG-INFO
yamltypes.egg-info/SOURCES.txt
yamltypes.egg-info/dependency_links.txt
yamltypes.egg-info/entry_points.txt
yamltypes.egg-info/requires.txt
yamltypes.egg-info/top_level.txt
yamltypes/tests/__init__.py
yamltypes/tests/test_util_yaml_config.py