Metadata-Version: 1.1
Name: yamltypes
Version: 1.0
Summary: tools for validating, documenting, and editing json and yaml data
Home-page: http://github.com/tardyp/yamltypes
Author: Pierre Tardy
Author-email: tardyp@gmail.com
License: BSD
Keywords: yaml,schema
Platform: Any
Classifier: License :: OSI Approved :: BSD License
Classifier: Programming Language :: Python
Classifier: Topic :: Software Development :: Libraries :: Python Modules
Classifier: Intended Audience :: Developers
